[ { "_id" : { "$oid" : "4f07a6bbfef97aec76000000"} , "answer1" : 0 , "answer2" : 1 , "answer3" : 1 , "choices" : 3 , "choice1" : "A" , "choice2" : "B" , "choice3" : "C" , "created" : "2012-01-07" , "modified" : "2012-01-07" , "owner" : "Markd" , "title" : "Velocity startup" , "voters" : [ "Markd" , "George"]} , { "_id" : { "$oid" : "4f2091cefef97a365d000000"} , "answer1" : 0 , "answer2" : 0 , "answer3" : 1 , "answer4" : 0 , "choices" : 4 , "choice1" : "5 hours" , "choice2" : "6 hours" , "choice3" : "7 hours" , "choice4" : "8 hours or more" , "created" : "2012-01-25" , "modified" : "2012-03-28" , "owner" : "George" , "title" : "How much sleep do you get each night?" , "voters" : [ "George"]} , { "_id" : { "$oid" : "4f6a56b0fef97a7572000000"} , "answer1" : 0 , "answer2" : 0 , "choices" : 2 , "choice1" : "Continue developing" , "choice2" : "Stop developing" , "created" : "2012-03-21" , "modified" : "2012-03-27" , "owner" : "George" , "title" : "First vote in a long long time" , "voters" : [ ]} , { "_id" : { "$oid" : "4f6a5d26fef97ad93f000000"} , "owner" : "George" , "voters" : [ "George"] , "title" : "Order votes in terms of dates" , "choice1" : "Yes" , "answer1" : 1 , "choice2" : "No" , "answer2" : 0 , "created" : "2012-03-21" , "modified" : "2012-03-21" , "choices" : 2} , { "_id" : { "$oid" : "4f6e3a74fef97a371d000000"} , "answer1" : 1 , "answer2" : 0 , "choices" : 2 , "choice1" : "Yes" , "choice2" : "No" , "created" : "2012-03-24" , "expire" : "0" , "modified" : "2012-03-28" , "owner" : "George" , "time" : 1332964919 , "title" : "Vote expire in one hour" , "voters" : [ "George"]} , { "_id" : { "$oid" : "4f6f66b2fef97a3f20000000"} , "owner" : "George" , "expire" : "9" , "time" : "1336526458" , "voters" : [ ] , "title" : "Vote expire in 10 hours" , "choice1" : "Yes" , "answer1" : 0 , "choice2" : "No" , "answer2" : 0 , "created" : "2012-03-25" , "modified" : "2012-05-09" , "choices" : 2} , { "_id" : { "$oid" : "4f931cd5fef97af13a000000"} , "owner" : "George" , "expire" : "20" , "time" : "1335043509" , "voters" : [ ] , "title" : "Test" , "choice1" : "1" , "answer1" : 0 , "choice2" : "2" , "answer2" : 0 , "created" : "2012-04-21" , "modified" : "2012-04-21" , "choices" : 2} , { "_id" : { "$oid" : "4fb27533fef97a1962000000"} , "owner" : "Qwer" , "expire" : "0" , "time" : "1337095472" , "voters" : [ ] , "title" : "Grace was here" , "choice1" : "Q" , "answer1" : 0 , "choice2" : "W" , "answer2" : 0 , "choice3" : "E" , "answer3" : 0 , "created" : "2012-05-15" , "modified" : "2012-05-15" , "choices" : 3} , { "_id" : { "$oid" : "4fb27591fef97a8a7a000000"} , "owner" : "Qwer" , "expire" : "0" , "time" : "1337095566" , "voters" : [ ] , "title" : "George teach me android programming" , "choice1" : "A" , "answer1" : 0 , "choice2" : "B" , "answer2" : 0 , "choice3" : "C" , "answer3" : 0 , "choice4" : "Ibm" , "answer4" : 0 , "created" : "2012-05-15" , "modified" : "2012-05-15" , "choices" : 4} ]